CHANGELOG.md
LICENSE
MANIFEST.in
README.md
exdesi.py
setup.py
exdesi.egg-info/PKG-INFO
exdesi.egg-info/SOURCES.txt
exdesi.egg-info/dependency_links.txt
exdesi.egg-info/requires.txt
exdesi.egg-info/top_level.txt
src/__init__.py
src/bioquali.py
src/query.py
src/sif_parser.py
src/utils.py
src/encodings/elementary_path_constraint.lp
src/encodings/find_best_experiment_sets.lp
src/encodings/heuristic.lp
src/encodings/some_path.lp