Metadata-Version: 2.1
Name: exdesi
Version: 0.4
Summary: Design experiments to differentiate interaction graph models.
Home-page: http://bioasp.github.io/exdesi/
Author: Sven Thiele
Author-email: sthiele78@gmail.com
License: GPLv3+
Platform: UNKNOWN
